ffsim/spin.py
ffsim/dimensions.py
ffsim/molecular_data.py
ffsim/_lib.abi3.so
ffsim/__init__.py
ffsim/cistring.py
ffsim/py.typed
ffsim/_lib.pyi
ffsim/gates/num_op_sum.py
ffsim/gates/__init__.py
ffsim/gates/diag_coulomb.py
ffsim/gates/orbital_rotation.py
ffsim/gates/basic_gates.py
ffsim/qiskit/transpiler_stages.py
ffsim/qiskit/sim.py
ffsim/qiskit/jordan_wigner.py
ffsim/qiskit/util.py
ffsim/qiskit/__init__.py
ffsim/qiskit/sampler.py
ffsim/qiskit/gates/num_num_ansatz.py
ffsim/qiskit/gates/givens_ansatz.py
ffsim/qiskit/gates/num_op_sum.py
ffsim/qiskit/gates/diag_coulomb_trotter.py
ffsim/qiskit/gates/ucj.py
ffsim/qiskit/gates/__init__.py
ffsim/qiskit/gates/diag_coulomb.py
ffsim/qiskit/gates/orbital_rotation.py
ffsim/qiskit/gates/slater_determinant.py
ffsim/qiskit/gates/double_factorized_trotter.py
ffsim/qiskit/transpiler_passes/drop_negligible.py
ffsim/qiskit/transpiler_passes/merge_orbital_rotations.py
ffsim/qiskit/transpiler_passes/__init__.py
ffsim/contract/num_op_sum.py
ffsim/contract/two_body.py
ffsim/contract/__init__.py
ffsim/contract/diag_coulomb.py
ffsim/contract/one_body.py
ffsim/linalg/predicates.py
ffsim/linalg/double_factorized_decomposition.py
ffsim/linalg/util.py
ffsim/linalg/__init__.py
ffsim/linalg/linalg.py
ffsim/linalg/givens.py
ffsim/optimize/__init__.py
ffsim/optimize/linear_method.py
ffsim/optimize/_util.py
ffsim/operators/common_operators.py
ffsim/operators/coupled_cluster.py
ffsim/operators/__init__.py
ffsim/operators/fermion_operator.py
ffsim/operators/fermion_action.py
ffsim/operators/fermi_hubbard.py
ffsim/_slow/__init__.py
ffsim/_slow/fermion_operator.py
ffsim/_slow/gates/num_op_sum.py
ffsim/_slow/gates/__init__.py
ffsim/_slow/gates/diag_coulomb.py
ffsim/_slow/gates/orbital_rotation.py
ffsim/_slow/contract/num_op_sum.py
ffsim/_slow/contract/__init__.py
ffsim/_slow/contract/diag_coulomb.py
ffsim/testing/__init__.py
ffsim/testing/testing.py
ffsim/trotter/__init__.py
ffsim-0.0.64.dist-info/RECORD
ffsim-0.0.64.dist-info/WHEEL
ffsim-0.0.64.dist-info/METADATA
ffsim-0.0.64.dist-info/licenses/LICENSE
