Metadata-Version: 2.4
Name: ffsim
Version: 0.0.64
Classifier: License :: OSI Approved :: Apache Software License
Classifier: Programming Language :: Python
Classifier: Programming Language :: Python :: 3 :: Only
Classifier: Programming Language :: Python :: 3.10
Classifier: Programming Language :: Python :: 3.11
Classifier: Programming Language :: Python :: 3.12
Classifier: Programming Language :: Python :: 3.13
Classifier: Programming Language :: Python :: 3.14
Classifier: Programming Language :: Rust
Classifier: Topic :: Scientific/Engineering :: Chemistry
Classifier: Topic :: Scientific/Engineering :: Physics
Classifier: Topic :: Software Development :: Libraries :: Python Modules
Requires-Dist: jax
Requires-Dist: numpy
Requires-Dist: opt-einsum
Requires-Dist: orjson
Requires-Dist: pyscf>=2.9
Requires-Dist: qiskit>=1.3
Requires-Dist: scipy
Requires-Dist: typing-extensions
Requires-Dist: coverage ; extra == 'dev'
Requires-Dist: maturin ; extra == 'dev'
Requires-Dist: mypy ; extra == 'dev'
Requires-Dist: myst-parser ; extra == 'dev'
Requires-Dist: nbmake ; extra == 'dev'
Requires-Dist: nbsphinx ; extra == 'dev'
Requires-Dist: pre-commit ; extra == 'dev'
Requires-Dist: pytest ; extra == 'dev'
Requires-Dist: qiskit[visualization] ; extra == 'dev'
Requires-Dist: qiskit-sphinx-theme ; extra == 'dev'
Requires-Dist: ruff==0.9.9 ; extra == 'dev'
Requires-Dist: sphinx ; extra == 'dev'
Requires-Dist: sphinx-autodoc-typehints ; extra == 'dev'
Provides-Extra: dev
License-File: LICENSE
Summary: Faster simulations of fermionic quantum circuits.
Requires-Python: >=3.10
Project-URL: Homepage, https://github.com/qiskit-community/ffsim
Project-URL: Documentation, https://qiskit-community.github.io/ffsim/
